westworld/__init__.py
westworld/_deprecated/__init__.py
westworld/_deprecated/agents.py
westworld/_deprecated/chicken_game.py
westworld/_deprecated/environment.py
westworld/_deprecated/sugarscape.py
westworld/agents/__init__.py
westworld/agents/agent.py
westworld/agents/collectible_finder.py
westworld/agents/sir_agent.py
westworld/algorithms/__init__.py
westworld/algorithms/neighbors.py
westworld/algorithms/pathfinding/__init__.py
westworld/algorithms/pathfinding/astar.py
westworld/algorithms/pathfinding/naive.py
westworld/algorithms/pathfinding/pathfinding.py
westworld/assets/__init__.py
westworld/assets/sprites/__init__.py
westworld/assets/sprites/arrow.py
westworld/assets/sprites/ball.py
westworld/assets/sprites/blob.py
westworld/assets/sprites/utils.py
westworld/colors.py
westworld/environment/__init__.py
westworld/environment/grid.py
westworld/environment/spatial.py
westworld/exceptions.py
westworld/logger.py
westworld/objects/__init__.py
westworld/objects/base_object.py
westworld/objects/collectible.py
westworld/objects/layer.py
westworld/objects/obstacle.py
westworld/objects/rectangle.py
westworld/objects/trigger.py
westworld/optimization/__init__.py
westworld/simulation/__init__.py
westworld/simulation/simulation.py
westworld/utils/__init__.py
westworld/utils/decorators.py
westworld/utils/image.py
westworld/utils/maze.py
westworld-0.1.3.dist-info/LICENSE
westworld-0.1.3.dist-info/WHEEL
westworld-0.1.3.dist-info/METADATA
westworld-0.1.3.dist-info/RECORD
