Metadata-Version: 2.1
Name: westworld
Version: 0.1.3
Summary: Multi-agent simulation library in Python
License: MIT
Author: Theo Alves Da Costa
Author-email: theo.alves.da.costa@gmail.com
Requires-Python: >=3.7,<3.10
Classifier: License :: OSI Approved :: MIT License
Classifier: Programming Language :: Python :: 3
Classifier: Programming Language :: Python :: 3.7
Classifier: Programming Language :: Python :: 3.8
Classifier: Programming Language :: Python :: 3.9
Requires-Dist: ffmpeg-python (>=0.2.0,<0.3.0)
Requires-Dist: imageio (>=2.9.0,<3.0.0)
Requires-Dist: matplotlib (>=3.4.2,<4.0.0)
Requires-Dist: numpy (>=1.21.0,<2.0.0)
Requires-Dist: pandas (>=1.3.0,<2.0.0)
Requires-Dist: pygame (>=2.0.1,<3.0.0)
Requires-Dist: scipy (>=1.7.1,<2.0.0)
Requires-Dist: tqdm (>=4.61.2,<5.0.0)
